davidkhala/azure/__init__.py
davidkhala/azure/auth.py
davidkhala/azure/ci.py
davidkhala/azure/subscription.py
davidkhala/azure/ai/__init__.py
davidkhala/azure/ai/agent.py
davidkhala/azure/ai/form.py
davidkhala/azure/ai/project.py
davidkhala/azure/ai/tools.py
davidkhala/azure/cli/__init__.py
davidkhala/azure/cli/ext.py
davidkhala/azure/monitor/__init__.py
davidkhala/azure/monitor/dce.py
davidkhala/azure/monitor/dcr.py
davidkhala/azure/monitor/ingestion.py
davidkhala/azure/monitor/log.py
davidkhala/azure/monitor/monitor.py
davidkhala/azure/recipe/blob.py
davidkhala/azure/storage/blob.py
davidkhala/azure/storage/community/blob.py
davidkhala_azure-0.0.9.dist-info/METADATA
davidkhala_azure-0.0.9.dist-info/WHEEL
davidkhala_azure-0.0.9.dist-info/RECORD
